shtomo-0.1.3.dist-info/METADATA
shtomo-0.1.3.dist-info/WHEEL
shtomo-0.1.3.dist-info/entry_points.txt
shtomo/__init__.py
shtomo/client.py
shtomo/parser_socks5_url.py
shtomo/shell_io.py
shtomo/shtomo.py
shtomo-0.1.3.dist-info/RECORD
