Metadata-Version: 2.1
Name: shtomo
Version: 0.1.3
Summary: shell's good friends
Author-Email: explorer <hsadkhk@gmail.com>
License: WTFPL
Requires-Python: >=3.8
Requires-Dist: cmd2~=2.4.3
Requires-Dist: pysocks
Requires-Dist: setuptools~=59.6.0
